ctxify/__init__.py
ctxify/cli.py
ctxify/content.py
ctxify/interactive.py
ctxify/utils.py
ctxify-0.3.0.dist-info/METADATA
ctxify-0.3.0.dist-info/WHEEL
ctxify-0.3.0.dist-info/entry_points.txt
ctxify-0.3.0.dist-info/licenses/LICENSE
ctxify-0.3.0.dist-info/RECORD
