Metadata-Version: 2.4
Name: ctxify
Version: 0.3.0
Summary: A tool to print git repository files with tree structure
License-File: LICENSE
Requires-Python: >=3.8
Requires-Dist: click
Requires-Dist: gitpython
Requires-Dist: prompt-toolkit>=3.0.50
